consoom.py
consoom-0.1.0.dist-info/WHEEL
consoom-0.1.0.dist-info/METADATA
consoom-0.1.0.dist-info/RECORD
