Metadata-Version: 2.1
Name: consoom
Version: 0.1.0
Summary: 
License: AGPL-3.0-only
Author: nhanb
Requires-Python: >=3.7,<4.0
Classifier: License :: OSI Approved :: GNU Affero General Public License v3
Classifier: Programming Language :: Python :: 3
Classifier: Programming Language :: Python :: 3.7
Classifier: Programming Language :: Python :: 3.8
Classifier: Programming Language :: Python :: 3.9
Requires-Dist: mistune (==2.0.0rc1)
Requires-Dist: urllib3 (>=1.26.5,<2.0.0)
